setup.py
zeanr_distributions/Binomialdistribution.py
zeanr_distributions/Gaussiandistribution.py
zeanr_distributions/Generaldistribution.py
zeanr_distributions/__init__.py
zeanr_distributions.egg-info/PKG-INFO
zeanr_distributions.egg-info/SOURCES.txt
zeanr_distributions.egg-info/dependency_links.txt
zeanr_distributions.egg-info/not-zip-safe
zeanr_distributions.egg-info/top_level.txt